<serviceModel xmlns:xsi="http://www.w3.org/2001/XMLSchema-instance" xmlns="http://www.metasolv.com/ServiceActivation/2003/ServiceModel">
  <description></description>
  <atomicService xsi:type="AtomicServiceType" name="A_ERIC_2-0_MOD_SUB_MOBILE_MSISDN">
    <description></description>
    <sendParameterCount>false</sendParameterCount>
    <parameter xsi:type="SimpleParameterType" name="MCLI">
      <description></description>
      <required>true</required>
      <default></default>
      <parameterValueMap>MCLI</parameterValueMap>
    </parameter>
    <parameter xsi:type="SimpleParameterType" name="IMSI">
      <description></description>
      <required>true</required>
      <default></default>
      <parameterValueMap>IMSI</parameterValueMap>
    </parameter>
    <parameter xsi:type="SimpleParameterType" name="MSISDN">
      <description></description>
      <required>true</required>
      <default></default>
      <parameterValueMap>MSISDN</parameterValueMap>
    </parameter>
    <parameter xsi:type="SimpleParameterType" name="OLD_MSISDN">
      <description></description>
      <required>true</required>
      <default></default>
      <parameterValueMap>OLD_MSISDN</parameterValueMap>
    </parameter>
  </atomicService>
  <atomicDeviceMap name="A_ERIC_2-0_MOD_SUB_MOBILE_MSISDN">
    <deviceMap>
      <vendor>ERIC</vendor>
      <type>MOBILE</type>
      <version>2-0</version>
      <implementation>com.oracle.activation.eric.mobile.x2_0.sub_mobile_msisdn.mod.generated.ModSub_mobile_msisdnProxy.execute</implementation>
      <interpreter>JINTERPRETER_PROGRAM</interpreter>
    </deviceMap>
  </atomicDeviceMap>
</serviceModel>